dataStructures/__init__.py
dataStructures/graphalgo_test.py
dataStructures/linear_test.py
dataStructures/linear/__init__.py
dataStructures/linear/cdll.py
dataStructures/linear/cdll_test.py
dataStructures/linear/csll.py
dataStructures/linear/dll.py
dataStructures/linear/queue_ll.py
dataStructures/linear/sll.py
dataStructures/linear/stack_ll.py
dataStructures/nodes/TNode.py
dataStructures/nodes/__init__.py
dataStructures/nodes/d_node.py
dataStructures/nodes/s_node.py
dataStructures/trees/AVL.py
dataStructures/trees/AVL_test.py
dataStructures/trees/BST.py
dataStructures/trees/__init__.py
dataStructures/trees/main.py
dataStructures/trees/test_AVL.py
dataStructures/trees/test_BST.py
dataStructures/trees/test_TNode.py
g41dataStructures-1.5.dist-info/METADATA
g41dataStructures-1.5.dist-info/WHEEL
g41dataStructures-1.5.dist-info/top_level.txt
g41dataStructures-1.5.dist-info/RECORD
