Metadata-Version: 2.1
Name: g41dataStructures
Version: 1.5
Summary: A library for data structures
